[{"msId":{"path":"/ts-basic-service/src/main/java/fdse/microservice/controller/BasicController.java","directoryName":""},"code":"@Autowired\n    BasicService service;","fieldClass":"BasicService","fieldVariable":"service","parentMethod":{"parentClassName":"BasicController","parentPackageName":"fdse.microservice.controller"},"line":21},{"msId":{"path":"/ts-admin-travel-service/src/main/java/admintravel/controller/AdminTravelController.java","directoryName":""},"code":"@Autowired\n    AdminTravelService adminTravelService;","fieldClass":"AdminTravelService","fieldVariable":"adminTravelService","parentMethod":{"parentClassName":"AdminTravelController","parentPackageName":"admintravel.controller"},"line":18},{"msId":{"path":"/ts-train-service/src/main/java/train/controller/TrainController.java","directoryName":""},"code":"@Autowired\n    private TrainService trainService;","fieldClass":"TrainService","fieldVariable":"trainService","parentMethod":{"parentClassName":"TrainController","parentPackageName":"train.controller"},"line":21},{"msId":{"path":"/ts-train-service/src/main/java/train/service/TrainServiceImpl.java","directoryName":""},"code":"@Autowired\n    private TrainTypeRepository repository;","fieldClass":"TrainTypeRepository","fieldVariable":"repository","parentMethod":{"parentClassName":"TrainServiceImpl","parentPackageName":"train.service"},"line":14},{"msId":{"path":"/ts-preserve-other-service/src/main/java/preserveOther/controller/PreserveOtherController.java","directoryName":""},"code":"@Autowired\n    private PreserveOtherService preserveService;","fieldClass":"PreserveOtherService","fieldVariable":"preserveService","parentMethod":{"parentClassName":"PreserveOtherController","parentPackageName":"preserveOther.controller"},"line":21},{"msId":{"path":"/ts-food-service/src/main/java/foodsearch/controller/FoodController.java","directoryName":""},"code":"@Autowired\n    FoodService foodService;","fieldClass":"FoodService","fieldVariable":"foodService","parentMethod":{"parentClassName":"FoodController","parentPackageName":"foodsearch.controller"},"line":18},{"msId":{"path":"/ts-food-service/src/main/java/foodsearch/service/FoodServiceImpl.java","directoryName":""},"code":"@Autowired\n    private FoodOrderRepository foodOrderRepository;","fieldClass":"FoodOrderRepository","fieldVariable":"foodOrderRepository","parentMethod":{"parentClassName":"FoodServiceImpl","parentPackageName":"foodsearch.service"},"line":29},{"msId":{"path":"/ts-inside-payment-service/src/main/java/inside_payment/controller/InsidePaymentController.java","directoryName":""},"code":"@Autowired\n    public InsidePaymentService service;","fieldClass":"InsidePaymentService","fieldVariable":"service","parentMethod":{"parentClassName":"InsidePaymentController","parentPackageName":"inside_payment.controller"},"line":21},{"msId":{"path":"/ts-inside-payment-service/src/main/java/inside_payment/service/InsidePaymentServiceImpl.java","directoryName":""},"code":"@Autowired\n    public AddMoneyRepository addMoneyRepository;","fieldClass":"AddMoneyRepository","fieldVariable":"addMoneyRepository","parentMethod":{"parentClassName":"InsidePaymentServiceImpl","parentPackageName":"inside_payment.service"},"line":27},{"msId":{"path":"/ts-inside-payment-service/src/main/java/inside_payment/service/InsidePaymentServiceImpl.java","directoryName":""},"code":"@Autowired\n    public PaymentRepository paymentRepository;","fieldClass":"PaymentRepository","fieldVariable":"paymentRepository","parentMethod":{"parentClassName":"InsidePaymentServiceImpl","parentPackageName":"inside_payment.service"},"line":30},{"msId":{"path":"/ts-assurance-service/src/main/java/assurance/controller/AssuranceController.java","directoryName":""},"code":"@Autowired\n    private AssuranceService assuranceService;","fieldClass":"AssuranceService","fieldVariable":"assuranceService","parentMethod":{"parentClassName":"AssuranceController","parentPackageName":"assurance.controller"},"line":22},{"msId":{"path":"/ts-assurance-service/src/main/java/assurance/service/AssuranceServiceImpl.java","directoryName":""},"code":"@Autowired\n    private AssuranceRepository assuranceRepository;","fieldClass":"AssuranceRepository","fieldVariable":"assuranceRepository","parentMethod":{"parentClassName":"AssuranceServiceImpl","parentPackageName":"assurance.service"},"line":22},{"msId":{"path":"/ts-admin-order-service/src/main/java/adminorder/controller/AdminOrderController.java","directoryName":""},"code":"@Autowired\n    AdminOrderService adminOrderService;","fieldClass":"AdminOrderService","fieldVariable":"adminOrderService","parentMethod":{"parentClassName":"AdminOrderController","parentPackageName":"adminorder.controller"},"line":19},{"msId":{"path":"/ts-notification-service/src/main/java/notification/controller/NotificationController.java","directoryName":""},"code":"@Autowired\n    NotificationService service;","fieldClass":"NotificationService","fieldVariable":"service","parentMethod":{"parentClassName":"NotificationController","parentPackageName":"notification.controller"},"line":17},{"msId":{"path":"/ts-notification-service/src/main/java/notification/service/NotificationServiceImpl.java","directoryName":""},"code":"@Autowired\n    MailService mailService;","fieldClass":"MailService","fieldVariable":"mailService","parentMethod":{"parentClassName":"NotificationServiceImpl","parentPackageName":"notification.service"},"line":23},{"msId":{"path":"/ts-station-service/src/main/java/fdse/microservice/controller/StationController.java","directoryName":""},"code":"@Autowired\n    private StationService stationService;","fieldClass":"StationService","fieldVariable":"stationService","parentMethod":{"parentClassName":"StationController","parentPackageName":"fdse.microservice.controller"},"line":23},{"msId":{"path":"/ts-station-service/src/main/java/fdse/microservice/service/StationServiceImpl.java","directoryName":""},"code":"@Autowired\n    private StationRepository repository;","fieldClass":"StationRepository","fieldVariable":"repository","parentMethod":{"parentClassName":"StationServiceImpl","parentPackageName":"fdse.microservice.service"},"line":17},{"msId":{"path":"/ts-ticketinfo-service/src/main/java/ticketinfo/controller/TicketInfoController.java","directoryName":""},"code":"@Autowired\n    TicketInfoService service;","fieldClass":"TicketInfoService","fieldVariable":"service","parentMethod":{"parentClassName":"TicketInfoController","parentPackageName":"ticketinfo.controller"},"line":20},{"msId":{"path":"/ts-cancel-service/src/main/java/cancel/controller/CancelController.java","directoryName":""},"code":"@Autowired\n    CancelService cancelService;","fieldClass":"CancelService","fieldVariable":"cancelService","parentMethod":{"parentClassName":"CancelController","parentPackageName":"cancel.controller"},"line":20},{"msId":{"path":"/ts-travel-service/src/main/java/travel/controller/TravelController.java","directoryName":""},"code":"@Autowired\n    private TravelService travelService;","fieldClass":"TravelService","fieldVariable":"travelService","parentMethod":{"parentClassName":"TravelController","parentPackageName":"travel.controller"},"line":26},{"msId":{"path":"/ts-travel-service/src/main/java/travel/service/TravelServiceImpl.java","directoryName":""},"code":"@Autowired\n    private TripRepository repository;","fieldClass":"TripRepository","fieldVariable":"repository","parentMethod":{"parentClassName":"TravelServiceImpl","parentPackageName":"travel.service"},"line":26},{"msId":{"path":"/ts-preserve-service/src/main/java/preserve/controller/PreserveController.java","directoryName":""},"code":"@Autowired\n    private PreserveService preserveService;","fieldClass":"PreserveService","fieldVariable":"preserveService","parentMethod":{"parentClassName":"PreserveController","parentPackageName":"preserve.controller"},"line":21},{"msId":{"path":"/ts-contacts-service/src/main/java/contacts/controller/ContactsController.java","directoryName":""},"code":"@Autowired\n    private ContactsService contactsService;","fieldClass":"ContactsService","fieldVariable":"contactsService","parentMethod":{"parentClassName":"ContactsController","parentPackageName":"contacts.controller"},"line":24},{"msId":{"path":"/ts-contacts-service/src/main/java/contacts/service/ContactsServiceImpl.java","directoryName":""},"code":"@Autowired\n    private ContactsRepository contactsRepository;","fieldClass":"ContactsRepository","fieldVariable":"contactsRepository","parentMethod":{"parentClassName":"ContactsServiceImpl","parentPackageName":"contacts.service"},"line":22},{"msId":{"path":"/ts-admin-user-service/src/main/java/adminuser/controller/AdminUserController.java","directoryName":""},"code":"@Autowired\n    AdminUserService adminUserService;","fieldClass":"AdminUserService","fieldVariable":"adminUserService","parentMethod":{"parentClassName":"AdminUserController","parentPackageName":"adminuser.controller"},"line":19},{"msId":{"path":"/ts-admin-user-service/src/main/java/adminuser/service/AdminUserServiceImpl.java","directoryName":""},"code":"private static final String USER_SERVICE_IP_URI \u003d \"http://ts-user-service:12342/api/v1/userservice/users\";","fieldClass":"String","fieldVariable":"USER_SERVICE_IP_URI","parentMethod":{"parentClassName":"AdminUserServiceImpl","parentPackageName":"adminuser.service"},"line":29},{"msId":{"path":"/ts-consign-price-service/src/main/java/consignprice/controller/ConsignPriceController.java","directoryName":""},"code":"@Autowired\n    ConsignPriceService service;","fieldClass":"ConsignPriceService","fieldVariable":"service","parentMethod":{"parentClassName":"ConsignPriceController","parentPackageName":"consignprice.controller"},"line":19},{"msId":{"path":"/ts-consign-price-service/src/main/java/consignprice/service/ConsignPriceServiceImpl.java","directoryName":""},"code":"@Autowired\n    private ConsignPriceConfigRepository repository;","fieldClass":"ConsignPriceConfigRepository","fieldVariable":"repository","parentMethod":{"parentClassName":"ConsignPriceServiceImpl","parentPackageName":"consignprice.service"},"line":18},{"msId":{"path":"/ts-payment-service/src/main/java/com/trainticket/controller/PaymentController.java","directoryName":""},"code":"@Autowired\n    PaymentService service;","fieldClass":"PaymentService","fieldVariable":"service","parentMethod":{"parentClassName":"PaymentController","parentPackageName":"com.trainticket.controller"},"line":20},{"msId":{"path":"/ts-payment-service/src/main/java/com/trainticket/service/PaymentServiceImpl.java","directoryName":""},"code":"@Autowired\n    PaymentRepository paymentRepository;","fieldClass":"PaymentRepository","fieldVariable":"paymentRepository","parentMethod":{"parentClassName":"PaymentServiceImpl","parentPackageName":"com.trainticket.service"},"line":23},{"msId":{"path":"/ts-payment-service/src/main/java/com/trainticket/service/PaymentServiceImpl.java","directoryName":""},"code":"@Autowired\n    AddMoneyRepository addMoneyRepository;","fieldClass":"AddMoneyRepository","fieldVariable":"addMoneyRepository","parentMethod":{"parentClassName":"PaymentServiceImpl","parentPackageName":"com.trainticket.service"},"line":26},{"msId":{"path":"/ts-price-service/src/main/java/price/controller/PriceController.java","directoryName":""},"code":"@Autowired\n    PriceService service;","fieldClass":"PriceService","fieldVariable":"service","parentMethod":{"parentClassName":"PriceController","parentPackageName":"price.controller"},"line":20},{"msId":{"path":"/ts-price-service/src/main/java/price/service/PriceServiceImpl.java","directoryName":""},"code":"@Autowired\n    private PriceConfigRepository priceConfigRepository;","fieldClass":"PriceConfigRepository","fieldVariable":"priceConfigRepository","parentMethod":{"parentClassName":"PriceServiceImpl","parentPackageName":"price.service"},"line":23},{"msId":{"path":"/ts-order-service/src/main/java/order/controller/OrderController.java","directoryName":""},"code":"@Autowired\n    private OrderService orderService;","fieldClass":"OrderService","fieldVariable":"orderService","parentMethod":{"parentClassName":"OrderController","parentPackageName":"order.controller"},"line":23},{"msId":{"path":"/ts-order-service/src/main/java/order/service/OrderServiceImpl.java","directoryName":""},"code":"@Autowired\n    private OrderRepository orderRepository;","fieldClass":"OrderRepository","fieldVariable":"orderRepository","parentMethod":{"parentClassName":"OrderServiceImpl","parentPackageName":"order.service"},"line":25},{"msId":{"path":"/ts-route-service/src/main/java/route/controller/RouteController.java","directoryName":""},"code":"@Autowired\n    private RouteService routeService;","fieldClass":"RouteService","fieldVariable":"routeService","parentMethod":{"parentClassName":"RouteController","parentPackageName":"route.controller"},"line":23},{"msId":{"path":"/ts-route-service/src/main/java/route/service/RouteServiceImpl.java","directoryName":""},"code":"@Autowired\n    private RouteRepository routeRepository;","fieldClass":"RouteRepository","fieldVariable":"routeRepository","parentMethod":{"parentClassName":"RouteServiceImpl","parentPackageName":"route.service"},"line":23},{"msId":{"path":"/ts-rebook-service/src/main/java/rebook/controller/RebookController.java","directoryName":""},"code":"@Autowired\n    RebookService service;","fieldClass":"RebookService","fieldVariable":"service","parentMethod":{"parentClassName":"RebookController","parentPackageName":"rebook.controller"},"line":21},{"msId":{"path":"/ts-verification-code-service/src/main/java/verifycode/controller/VerifyCodeController.java","directoryName":""},"code":"@Autowired\n    private VerifyCodeService verifyCodeService;","fieldClass":"VerifyCodeService","fieldVariable":"verifyCodeService","parentMethod":{"parentClassName":"VerifyCodeController","parentPackageName":"verifycode.controller"},"line":26},{"msId":{"path":"/ts-security-service/src/main/java/security/controller/SecurityController.java","directoryName":""},"code":"@Autowired\n    private SecurityService securityService;","fieldClass":"SecurityService","fieldVariable":"securityService","parentMethod":{"parentClassName":"SecurityController","parentPackageName":"security.controller"},"line":21},{"msId":{"path":"/ts-security-service/src/main/java/security/service/SecurityServiceImpl.java","directoryName":""},"code":"@Autowired\n    private SecurityRepository securityRepository;","fieldClass":"SecurityRepository","fieldVariable":"securityRepository","parentMethod":{"parentClassName":"SecurityServiceImpl","parentPackageName":"security.service"},"line":28},{"msId":{"path":"/ts-admin-basic-info-service/src/main/java/adminbasic/controller/AdminBasicInfoController.java","directoryName":""},"code":"@Autowired\n    AdminBasicInfoService adminBasicInfoService;","fieldClass":"AdminBasicInfoService","fieldVariable":"adminBasicInfoService","parentMethod":{"parentClassName":"AdminBasicInfoController","parentPackageName":"adminbasic.controller"},"line":21},{"msId":{"path":"/ts-seat-service/src/main/java/seat/controller/SeatController.java","directoryName":""},"code":"@Autowired\n    private SeatService seatService;","fieldClass":"SeatService","fieldVariable":"seatService","parentMethod":{"parentClassName":"SeatController","parentPackageName":"seat.controller"},"line":19},{"msId":{"path":"/ts-travel2-service/src/main/java/travel2/controller/Travel2Controller.java","directoryName":""},"code":"@Autowired\n    private Travel2Service service;","fieldClass":"Travel2Service","fieldVariable":"service","parentMethod":{"parentClassName":"Travel2Controller","parentPackageName":"travel2.controller"},"line":25},{"msId":{"path":"/ts-travel2-service/src/main/java/travel2/service/Travel2ServiceImpl.java","directoryName":""},"code":"@Autowired\n    TripRepository repository;","fieldClass":"TripRepository","fieldVariable":"repository","parentMethod":{"parentClassName":"Travel2ServiceImpl","parentPackageName":"travel2.service"},"line":26},{"msId":{"path":"/ts-order-other-service/src/main/java/other/controller/OrderOtherController.java","directoryName":""},"code":"@Autowired\n    private OrderOtherService orderService;","fieldClass":"OrderOtherService","fieldVariable":"orderService","parentMethod":{"parentClassName":"OrderOtherController","parentPackageName":"other.controller"},"line":23},{"msId":{"path":"/ts-order-other-service/src/main/java/other/service/OrderOtherServiceImpl.java","directoryName":""},"code":"@Autowired\n    private OrderOtherRepository orderOtherRepository;","fieldClass":"OrderOtherRepository","fieldVariable":"orderOtherRepository","parentMethod":{"parentClassName":"OrderOtherServiceImpl","parentPackageName":"other.service"},"line":25},{"msId":{"path":"/ts-food-map-service/src/main/java/food/controller/FoodStoreController.java","directoryName":""},"code":"@Autowired\n    FoodMapService foodMapService;","fieldClass":"FoodMapService","fieldVariable":"foodMapService","parentMethod":{"parentClassName":"FoodStoreController","parentPackageName":"food.controller"},"line":19},{"msId":{"path":"/ts-food-map-service/src/main/java/food/controller/TrainFoodController.java","directoryName":""},"code":"@Autowired\n    FoodMapService foodMapService;","fieldClass":"FoodMapService","fieldVariable":"foodMapService","parentMethod":{"parentClassName":"TrainFoodController","parentPackageName":"food.controller"},"line":17},{"msId":{"path":"/ts-food-map-service/src/main/java/food/service/FoodMapServiceImpl.java","directoryName":""},"code":"@Autowired\n    FoodStoreRepository foodStoreRepository;","fieldClass":"FoodStoreRepository","fieldVariable":"foodStoreRepository","parentMethod":{"parentClassName":"FoodMapServiceImpl","parentPackageName":"food.service"},"line":20},{"msId":{"path":"/ts-food-map-service/src/main/java/food/service/FoodMapServiceImpl.java","directoryName":""},"code":"@Autowired\n    TrainFoodRepository trainFoodRepository;","fieldClass":"TrainFoodRepository","fieldVariable":"trainFoodRepository","parentMethod":{"parentClassName":"FoodMapServiceImpl","parentPackageName":"food.service"},"line":23},{"msId":{"path":"/ts-consign-service/src/main/java/consign/controller/ConsignController.java","directoryName":""},"code":"@Autowired\n    ConsignService service;","fieldClass":"ConsignService","fieldVariable":"service","parentMethod":{"parentClassName":"ConsignController","parentPackageName":"consign.controller"},"line":21},{"msId":{"path":"/ts-consign-service/src/main/java/consign/service/ConsignServiceImpl.java","directoryName":""},"code":"@Autowired\n    ConsignRepository repository;","fieldClass":"ConsignRepository","fieldVariable":"repository","parentMethod":{"parentClassName":"ConsignServiceImpl","parentPackageName":"consign.service"},"line":26},{"msId":{"path":"/ts-auth-service/src/main/java/auth/controller/AuthController.java","directoryName":""},"code":"@Autowired\n    private UserService userService;","fieldClass":"UserService","fieldVariable":"userService","parentMethod":{"parentClassName":"AuthController","parentPackageName":"auth.controller"},"line":19},{"msId":{"path":"/ts-auth-service/src/main/java/auth/controller/UserController.java","directoryName":""},"code":"@Autowired\n    private UserService userService;","fieldClass":"UserService","fieldVariable":"userService","parentMethod":{"parentClassName":"UserController","parentPackageName":"auth.controller"},"line":25},{"msId":{"path":"/ts-auth-service/src/main/java/auth/controller/UserController.java","directoryName":""},"code":"@Autowired\n    private TokenService tokenService;","fieldClass":"TokenService","fieldVariable":"tokenService","parentMethod":{"parentClassName":"UserController","parentPackageName":"auth.controller"},"line":28},{"msId":{"path":"/ts-auth-service/src/main/java/auth/security/UserDetailsServiceImpl.java","directoryName":""},"code":"@Autowired\n    private UserRepository userRepository;","fieldClass":"UserRepository","fieldVariable":"userRepository","parentMethod":{"parentClassName":"UserDetailsServiceImpl","parentPackageName":"auth.security"},"line":21},{"msId":{"path":"/ts-auth-service/src/main/java/auth/service/impl/UserServiceImpl.java","directoryName":""},"code":"@Autowired\n    private UserRepository userRepository;","fieldClass":"UserRepository","fieldVariable":"userRepository","parentMethod":{"parentClassName":"UserServiceImpl","parentPackageName":"auth.service.impl"},"line":28},{"msId":{"path":"/ts-auth-service/src/main/java/auth/service/impl/TokenServiceImpl.java","directoryName":""},"code":"@Autowired\n    private UserRepository userRepository;","fieldClass":"UserRepository","fieldVariable":"userRepository","parentMethod":{"parentClassName":"TokenServiceImpl","parentPackageName":"auth.service.impl"},"line":38},{"msId":{"path":"/ts-user-service/src/main/java/user/controller/UserController.java","directoryName":""},"code":"@Autowired\n    private UserService userService;","fieldClass":"UserService","fieldVariable":"userService","parentMethod":{"parentClassName":"UserController","parentPackageName":"user.controller"},"line":23},{"msId":{"path":"/ts-user-service/src/main/java/user/service/impl/UserServiceImpl.java","directoryName":""},"code":"@Autowired\n    private UserRepository userRepository;","fieldClass":"UserRepository","fieldVariable":"userRepository","parentMethod":{"parentClassName":"UserServiceImpl","parentPackageName":"user.service.impl"},"line":28},{"msId":{"path":"/ts-user-service/src/main/java/user/service/impl/UserServiceImpl.java","directoryName":""},"code":"private static final String AUTH_SERVICE_URI \u003d \"http://ts-auth-service:12340/api/v1\";","fieldClass":"String","fieldVariable":"AUTH_SERVICE_URI","parentMethod":{"parentClassName":"UserServiceImpl","parentPackageName":"user.service.impl"},"line":32},{"msId":{"path":"/ts-travel-plan-service/src/main/java/travelplan/controller/TravelPlanController.java","directoryName":""},"code":"@Autowired\n    TravelPlanService travelPlanService;","fieldClass":"TravelPlanService","fieldVariable":"travelPlanService","parentMethod":{"parentClassName":"TravelPlanController","parentPackageName":"travelplan.controller"},"line":22},{"msId":{"path":"/ts-route-plan-service/src/main/java/plan/controller/RoutePlanController.java","directoryName":""},"code":"@Autowired\n    private RoutePlanService routePlanService;","fieldClass":"RoutePlanService","fieldVariable":"routePlanService","parentMethod":{"parentClassName":"RoutePlanController","parentPackageName":"plan.controller"},"line":21},{"msId":{"path":"/ts-admin-route-service/src/main/java/adminroute/controller/AdminRouteController.java","directoryName":""},"code":"@Autowired\n    AdminRouteService adminRouteService;","fieldClass":"AdminRouteService","fieldVariable":"adminRouteService","parentMethod":{"parentClassName":"AdminRouteController","parentPackageName":"adminroute.controller"},"line":19},{"msId":{"path":"/ts-config-service/src/main/java/config/controller/ConfigController.java","directoryName":""},"code":"@Autowired\n    private ConfigService configService;","fieldClass":"ConfigService","fieldVariable":"configService","parentMethod":{"parentClassName":"ConfigController","parentPackageName":"config.controller"},"line":23},{"msId":{"path":"/ts-config-service/src/main/java/config/service/ConfigServiceImpl.java","directoryName":""},"code":"@Autowired\n    ConfigRepository repository;","fieldClass":"ConfigRepository","fieldVariable":"repository","parentMethod":{"parentClassName":"ConfigServiceImpl","parentPackageName":"config.service"},"line":19}]